point_in_geojson_jaluebbe-0.0.5.dist-info/METADATA
point_in_geojson_jaluebbe-0.0.5.dist-info/WHEEL
point_in_geojson_jaluebbe-0.0.5.dist-info/license_files/LICENSE
point_in_geojson/__init__.py
point_in_geojson/point_in_geojson.cpython-311-darwin.so
point_in_geojson_jaluebbe-0.0.5.dist-info/RECORD
